sysfunc/__init__.py
sysfunc/pyarmor_runtime_000000/__init__.py
sysfunc/pyarmor_runtime_000000/pyarmor_runtime.pyd
sysfunc-0.8.dist-info/METADATA
sysfunc-0.8.dist-info/WHEEL
sysfunc-0.8.dist-info/top_level.txt
sysfunc-0.8.dist-info/RECORD
