Metadata-Version: 2.1
Name: sysfunc
Version: 0.8
Summary: A library for interacting with system functions
Author: Hosne432
Classifier: Programming Language :: Python :: 3
Classifier: License :: OSI Approved :: MIT License
Classifier: Operating System :: OS Independent
Requires-Python: ==3.12.*
